uncpath/__init__.py
uncpath/cli.py
uncpath/config.py
uncpath/exceptions.py
uncpath/mapper.py
uncpath/parser.py
uncpath-0.1.0.dist-info/METADATA
uncpath-0.1.0.dist-info/WHEEL
uncpath-0.1.0.dist-info/entry_points.txt
uncpath-0.1.0.dist-info/licenses/LICENSE
uncpath-0.1.0.dist-info/RECORD
